industryDocumentsWrapper/__init__.py
industryDocumentsWrapper/test.ipynb
industryDocumentsWrapper/ucsf_api.py
industrydocumentswrapper-0.112.dist-info/LICENSE
industrydocumentswrapper-0.112.dist-info/METADATA
industrydocumentswrapper-0.112.dist-info/WHEEL
industrydocumentswrapper-0.112.dist-info/RECORD
