Metadata-Version: 2.1
Name: industryDocumentsWrapper
Version: 0.112
Summary: A simple python wrapper for the UCSF Industry Documents API.
Home-page: https://github.com/UNC-Libraries/UCSF-Industry-Docs-API-Python-Wrapper
License: Apache-2.0
Keywords: UCSF,Industry Documents,API,JUUL
Author: Rolando Rodriguez
Author-email: rolando@ad.unc.edu
Maintainer: Rolando Rodriguez
Maintainer-email: rolando@ad.unc.edu
Requires-Python: >=3.12,<4.0
Classifier: License :: OSI Approved :: Apache Software License
Classifier: Programming Language :: Python :: 3
Classifier: Programming Language :: Python :: 3.12
Classifier: Programming Language :: Python :: 3.13
Requires-Dist: polars (>=1.14.0,<2.0.0)
Requires-Dist: requests (>=2.32.3,<3.0.0)
Project-URL: Repository, https://github.com/UNC-Libraries/UCSF-Industry-Docs-API-Python-Wrapper
